README.rst
setup.py
sense/__init__.py
sense/resources.py
sense/utils.py
sense/version.py
sense_python_client.egg-info/PKG-INFO
sense_python_client.egg-info/SOURCES.txt
sense_python_client.egg-info/dependency_links.txt
sense_python_client.egg-info/requires.txt
sense_python_client.egg-info/top_level.txt