Metadata-Version: 1.1
Name: sense-python-client
Version: 1.0.0
Summary: Sen.se API client
Home-page: https://sen.se/developers/
Author: Sen.se
Author-email: api@sen.se
License: MIT
Platform: UNKNOWN
Classifier: Development Status :: 4 - Beta
Classifier: License :: OSI Approved :: MIT License
Classifier: Environment :: Web Environment
Classifier: Intended Audience :: Developers
Classifier: Operating System :: OS Independent
Classifier: Programming Language :: Python
Classifier: Programming Language :: Python :: 2.7
Classifier: Topic :: Software Development :: Libraries :: Python Modules
